railtracks_cli/__init__.py
railtracks_cli/__main__.py
railtracks_cli-1.115.dist-info/entry_points.txt
railtracks_cli-1.115.dist-info/licenses/LICENSE
railtracks_cli-1.115.dist-info/WHEEL
railtracks_cli-1.115.dist-info/METADATA
railtracks_cli-1.115.dist-info/RECORD
