Metadata-Version: 2.4
Name: railtracks-cli
Version: 1.115
Summary: railtracks - A Python development server with file watching and JSON API
Author-email: Logan Underwood <logan@railtown.ai>, Levi Varsanyi <levi@railtown.ai>, Jaime Bueza <jaime@railtown.ai>, Amir Refaee <amir@railtown.ai>, Aryan Ballani <aryan@railtown.ai>, Tristan Brown <tristan@railtown.ai>
Requires-Python: >=3.10
Classifier: Programming Language :: Python :: 3
Classifier: Programming Language :: Python :: 3.9
Classifier: Programming Language :: Python :: 3.10
Classifier: Programming Language :: Python :: 3.11
Classifier: Programming Language :: Python :: 3.12
Classifier: License :: OSI Approved :: MIT License
Classifier: Operating System :: OS Independent
Classifier: Development Status :: 4 - Beta
Classifier: Intended Audience :: Developers
Classifier: Intended Audience :: Science/Research
Classifier: Natural Language :: English
Classifier: Topic :: Scientific/Engineering :: Artificial Intelligence
Classifier: Topic :: Software Development :: Libraries :: Application Frameworks
Classifier: Environment :: Console
Classifier: Typing :: Typed
License-File: LICENSE
Requires-Dist: railtracks
Requires-Dist: watchdog >= 3.0.0
Project-URL: Release Notes, https://github.com/RailtownAI/railtracks/releases
Project-URL: documentation, https://railtownai.github.io/railtracks/
Project-URL: home, https://railtracks.org
Project-URL: repository, https://github.com/RailtownAI/railtracks
